TOPSIS_KHUSHI_102016099/__init__.py
TOPSIS_KHUSHI_102016099/topsis.py
TOPSIS_KHUSHI_102016099-1.2.2.dist-info/LICENSE.txt
TOPSIS_KHUSHI_102016099-1.2.2.dist-info/METADATA
TOPSIS_KHUSHI_102016099-1.2.2.dist-info/WHEEL
TOPSIS_KHUSHI_102016099-1.2.2.dist-info/top_level.txt
TOPSIS_KHUSHI_102016099-1.2.2.dist-info/RECORD
